<?xml version="1.0" encoding="utf-8" standalone="yes" ?>
<T3locallang>
	<meta type="array">
		<type>module</type>
		<description>Language labels for plugin &quot;tx_qzcompanylist_pi1&quot;</description>
	</meta>
	<data type="array">
		<languageKey index="default" type="array">
			<label index="searchButtonLabel">Search</label>
			<label index="searchOrLabel">All words (AND)</label>
			<label index="searchAndLabel">One of the words (OR)</label>
		</languageKey>
		<languageKey index="de" type="array">
			<label index="searchButtonLabel">Suchen</label>
			<label index="searchOrLabel">Alle Wörter (UND)</label>
			<label index="searchAndLabel">Eines der Wörter (ODER)</label>
		</languageKey>
	</data>
</T3locallang>